README.md
setup.cfg
setup.py
googledevices/__init__.py
googledevices/helpers.py
googledevices.egg-info/PKG-INFO
googledevices.egg-info/SOURCES.txt
googledevices.egg-info/dependency_links.txt
googledevices.egg-info/entry_points.txt
googledevices.egg-info/requires.txt
googledevices.egg-info/top_level.txt
googledevices/api/__init__.py
googledevices/api/connect.py
googledevices/api/cast/__init__.py
googledevices/api/cast/assistant.py
googledevices/api/cast/bluetooth.py
googledevices/api/cast/info.py
googledevices/api/cast/settings.py
googledevices/api/cast/wifi.py
googledevices/api/wifi/__init__.py
googledevices/api/wifi/clients.py
googledevices/api/wifi/info.py
googledevices/cli/__init__.py
googledevices/cli/cli.py
googledevices/cli/commands/__init__.py
googledevices/cli/commands/alarm_volume.py
googledevices/cli/commands/all_devices.py
googledevices/cli/commands/bluetooth_devices.py
googledevices/cli/commands/debug.py
googledevices/cli/commands/device_info.py
googledevices/cli/commands/googlewifi.py
googledevices/cli/commands/info.py
googledevices/cli/commands/reboot.py
googledevices/cli/commands/scan_network.py
googledevices/utils/__init__.py
googledevices/utils/const.py
googledevices/utils/convert.py
googledevices/utils/debug.py
googledevices/utils/log.py
googledevices/utils/scan.py
googledevices/utils/test_all.py