Metadata-Version: 2.1
Name: googledevices
Version: 1.0.0
Summary: Get information from, and control various Google devices.
Home-page: https://github.com/ludeeus/googledevices
Author: Joakim Sorensen
Author-email: ludeeus@gmail.com
License: MIT
Platform: UNKNOWN
Classifier: Programming Language :: Python :: 3
Classifier: License :: OSI Approved :: MIT License
Classifier: Operating System :: OS Independent
